python_workq-0.1.dist-info/DESCRIPTION.rst
python_workq-0.1.dist-info/METADATA
python_workq-0.1.dist-info/metadata.json
python_workq-0.1.dist-info/RECORD
python_workq-0.1.dist-info/top_level.txt
python_workq-0.1.dist-info/WHEEL
workq/__init__.py
workq/_version.py
workq/error.py
workq/job.py
workq/workq.py
