Metadata-Version: 2.0
Name: python-workq
Version: 0.1
Summary: Python Client for Workq
Home-page: https://github.com/hhatto/python-workq
Author: Hideo Hattori
Author-email: hhatto.jp@gmail.com
License: MIT License
Keywords: job queue
Platform: UNKNOWN
Classifier: Development Status :: 3 - Alpha
Classifier: Programming Language :: Python
Classifier: Programming Language :: Python :: 3
